lab2_sequence_detector/sequence_mealy.v
// sequence_mealy.v
// Mealy FSM: 时序检测器（连续3个1检测）
// 输出取决于当前状态和当前输入：
//   在S2或S3状态下，若输入为1则输出1；否则输出0
// 状态编码：
//   S0 = 2'b00  已检测到0个连续1
//   S1 = 2'b01  已检测到1个连续1
//   S2 = 2'b10  已检测到2个连续1
//   S3 = 2'b11  已检测到3+个连续1

module sequence_mealy (
    input  wire clk,
    input  wire rst,
    input  wire din,
    output reg  dout
);

    parameter S0 = 2'b00;
    parameter S1 = 2'b01;
    parameter S2 = 2'b10;
    parameter S3 = 2'b11;

    reg [1:0] state;

    // 状态寄存器（异步复位）
    always @(posedge clk or posedge rst) begin
        if (rst)
            state <= S0;
        else
            case (state)
                S0: state <= din ? S1 : S0;
                S1: state <= din ? S2 : S0;
                S2: state <= din ? S3 : S0;
                S3: state <= din ? S3 : S0;
                default: state <= S0;
            endcase
    end

    // 输出逻辑（Mealy：取决于当前状态和当前输入）
    always @(*) begin
        case (state)
            S2:      dout = din ? 1'b1 : 1'b0;
            S3:      dout = din ? 1'b1 : 1'b0;
            default: dout = 1'b0;
        endcase
    end

endmodule

lab2_sequence_detector/sequence_moore.v
// sequence_moore.v
// Moore FSM: 时序检测器（连续3个1检测）
// 状态输出：S3时输出1，其余状态输出0
// 状态编码：
//   S0 = 2'b00  已检测到0个连续1
//   S1 = 2'b01  已检测到1个连续1
//   S2 = 2'b10  已检测到2个连续1
//   S3 = 2'b11  已检测到3个连续1（输出1）

module sequence_moore (
    input  wire clk,
    input  wire rst,
    input  wire din,
    output reg  dout
);

    parameter S0 = 2'b00;
    parameter S1 = 2'b01;
    parameter S2 = 2'b10;
    parameter S3 = 2'b11;

    reg [1:0] state;

    // 状态寄存器（异步复位）
    always @(posedge clk or posedge rst) begin
        if (rst)
            state <= S0;
        else
            case (state)
                S0: state <= din ? S1 : S0;
                S1: state <= din ? S2 : S0;
                S2: state <= din ? S3 : S0;
                S3: state <= din ? S3 : S0;
                default: state <= S0;
            endcase
    end

    // 输出逻辑（Moore：仅取决于当前状态）
    always @(*) begin
        case (state)
            S3:      dout = 1'b1;
            default: dout = 1'b0;
        endcase
    end

endmodule

lab2_sequence_detector/tb_sequence.v
// tb_sequence.v
// 仿真激励：data = 'b11011_0111_0111（13位，高位先输入）
// 序列展开：1 1 0 1 1 0 1 1 1 0 1 1 1
// 同时仿真Moore型和Mealy型自动机

`timescale 1ns/1ps

module tb_sequence;

    reg        clk;
    reg        rst;
    reg        din;
    wire       moore_out;
    wire       mealy_out;

    // 例化Moore型自动机
    sequence_moore u_moore (
        .clk  (clk),
        .rst  (rst),
        .din  (din),
        .dout (moore_out)
    );

    // 例化Mealy型自动机
    sequence_mealy u_mealy (
        .clk  (clk),
        .rst  (rst),
        .din  (din),
        .dout (mealy_out)
    );

    // 时钟：周期10ns
    initial clk = 0;
    always #5 clk = ~clk;

    // 仿真数据：data = 'b11011_0111_0111
    reg [12:0] data = 13'b1101101110111;
    integer i;

    initial begin
        $dumpfile("tb_sequence.vcd");
        $dumpvars(0, tb_sequence);

        // 复位
        rst = 1;
        din = 0;
        @(negedge clk); #1;
        @(negedge clk); #1;
        rst = 0;

        // 从高位到低位逐位输入
        for (i = 12; i >= 0; i = i - 1) begin
            @(negedge clk); #1;
            din = data[i];
        end

        // 额外空闲周期
        @(negedge clk); #1; din = 0;
        @(negedge clk); #1; din = 0;

        #20;
        $finish;
    end

    // 监视输出
    initial begin
        $display("Time  clk rst din | Moore_state Moore_out | Mealy_state Mealy_out");
        $monitor("%4t   %b   %b   %b  |     %b          %b     |     %b          %b",
                 $time, clk, rst, din,
                 u_moore.state, moore_out,
                 u_mealy.state, mealy_out);
    end

endmodule

lab2_sequence_detector/tb_sequence.vcd
$date
	Thu Mar 26 08:36:36 2026
$end
$version
	Icarus Verilog
$end
$timescale
	1ps
$end
$scope module tb_sequence $end
$var wire 1 ! moore_out $end
$var wire 1 " mealy_out $end
$var reg 1 # clk $end
$var reg 13 $ data [12:0] $end
$var reg 1 % din $end
$var reg 1 & rst $end
$var integer 32 ' i [31:0] $end
$scope module u_mealy $end
$var wire 1 # clk $end
$var wire 1 % din $end
$var wire 1 & rst $end
$var parameter 2 ( S0 $end
$var parameter 2 ) S1 $end
$var parameter 2 * S2 $end
$var parameter 2 + S3 $end
$var reg 1 " dout $end
$var reg 2 , state [1:0] $end
$upscope $end
$scope module u_moore $end
$var wire 1 # clk $end
$var wire 1 % din $end
$var wire 1 & rst $end
$var parameter 2 - S0 $end
$var parameter 2 . S1 $end
$var parameter 2 / S2 $end
$var parameter 2 0 S3 $end
$var reg 1 ! dout $end
$var reg 2 1 state [1:0] $end
$upscope $end
$upscope $end
$enddefinitions $end
$comment Show the parameter values. $end
$dumpall
b11 0
b10 /
b1 .
b0 -
b11 +
b10 *
b1 )
b0 (
$end
#0
$dumpvars
b0 1
b0 ,
bx '
1&
0%
b1101101110111 $
0#
0"
0!
$end
#5000
1#
#10000
0#
#15000
1#
#20000
0#
#21000
b1100 '
0&
#25000
1#
#30000
0#
#31000
b1011 '
1%
#35000
b1 1
b1 ,
1#
#40000
0#
#41000
b1010 '
#45000
1"
b10 ,
b10 1
1#
#50000
0#
#51000
0"
b1001 '
0%
#55000
b0 1
b0 ,
1#
#60000
0#
#61000
b1000 '
1%
#65000
b1 ,
b1 1
1#
#70000
0#
#71000
b111 '
#75000
1"
b10 1
b10 ,
1#
#80000
0#
#81000
0"
b110 '
0%
#85000
b0 ,
b0 1
1#
#90000
0#
#91000
b101 '
1%
#95000
b1 1
b1 ,
1#
#100000
0#
#101000
b100 '
#105000
1"
b10 ,
b10 1
1#
#110000
0#
#111000
b11 '
#115000
1!
b11 1
b11 ,
1#
#120000
0#
#121000
0"
b10 '
0%
#125000
0!
b0 ,
b0 1
1#
#130000
0#
#131000
b1 '
1%
#135000
b1 1
b1 ,
1#
#140000
0#
#141000
b0 '
#145000
1"
b10 ,
b10 1
1#
#150000
0#
#151000
b11111111111111111111111111111111 '
#155000
1!
b11 1
b11 ,
1#
#160000
0#
#161000
0"
0%
#165000
0!
b0 ,
b0 1
1#
